<?xml version="1.0"?>
<tool_dependency>
    <package name="numpy" version="1.7.1">
        <repository name="package_numpy_1_7" owner="iuc" prior_installation_required="True" />
    </package>
    <package name="matplotlib" version="1.2.1">
        <repository name="package_matplotlib_1_2" owner="iuc" prior_installation_required="True" />
    </package>
    <package name="htseq" version="0.6.1">
        <install version="1.0">
            <actions>
                <action type="download_by_url" sha256sum="9bff6779595ea13c10137dad3bc4ecfd046b0bc620990eaa08920a29dcbd05c5">https://depot.galaxyproject.org/software/htseq/htseq_0.6_src_all.tar.gz</action>
                <action type="set_environment_for_install">
                    <repository name="package_numpy_1_7" owner="iuc">
                        <package name="numpy" version="1.7.1" />
                    </repository>
                    <repository name="package_matplotlib_1_2" owner="iuc">
                        <package name="matplotlib" version="1.2.1" />
                    </repository>
                </action>
                <action type="make_directory">$INSTALL_DIR/lib/python</action>
                <action type="shell_command">
                    export PYTHONPATH=$PYTHONPATH:$INSTALL_DIR/lib/python &amp;&amp;
                    python setup.py install --install-lib $INSTALL_DIR/lib/python --install-scripts $INSTALL_DIR/bin</action>
                <action type="set_environment">
                    <environment_variable action="prepend_to" name="PYTHONPATH">$INSTALL_DIR/lib/python</environment_variable>
                    <environment_variable action="prepend_to" name="PATH">$INSTALL_DIR/bin</environment_variable>
                    <environment_variable action="prepend_to" name="PYTHONPATH">$ENV[PYTHONPATH_NUMPY]</environment_variable>
                    <environment_variable action="prepend_to" name="PATH">$ENV[PATH_NUMPY]</environment_variable>
                    <environment_variable action="prepend_to" name="PYTHONPATH">$ENV[PYTHONPATH_MATPLOTLIB]</environment_variable>
                    <environment_variable action="set_to" name="HTSEQ_ROOT_PATH">$INSTALL_DIR</environment_variable>
                </action>
            </actions>
        </install>
        <readme>
            Installation of htseq. The installation can be accessed via HTSEQ_ROOT_PATH.
            https://pypi.python.org/pypi/HTSeq
        </readme>
    </package>
</tool_dependency>
