<macros>
    <token name="@VERSION@">1.0.0</token>
    <xml name="requirements">
        <requirements>
            <requirement type="package" version="3.3.1">r-base</requirement>
            <requirement type="package" version="@VERSION@">bioconductor-iwtomics</requirement>
        </requirements>
    </xml>
    <xml name="citations">
        <citations>
            <citation type="bibtex">
                @ARTICLE{
                        iwt-functional-data,
                        author = {Pini, Alessia and Vantini, Simone},
                        title = {Interval-Wise Testing for functional data},
                        journal = {Journal of Nonparametric Statistics},
                        year = {2017},
                        volume = {29},
                        number = {2},
                        pages = {407-424}
                }
            </citation>
            <citation type="bibtex">
                @MANUAL{
                        iwtomics,
                        author = {Cremona, Marzia A and Pini, Alessia and Chiaromonte, Francesca and Vantini, Simone},
                        title = {IWTomics: Interval-Wise Testing for Omics Data},
                        note = {R package version 1.0.0},
                        year = {2017}
                }
            </citation>
        </citations>
    </xml>
</macros>