<tool id="enzywizard_integrate" name="EnzyWizard Integrate" version="@TOOL_VERSION@+galaxy@VERSION_SUFFIX@" profile="@PROFILE@">
    <description>Integrate multiple EnzyWizard JSON reports into a graph representation</description>
    <macros>
        <import>macros.xml</import>
    </macros>
    <requirements>
        <requirement type="package" version="@TOOL_VERSION@">enzywizard-integrate</requirement>
        <requirement type="package">unzip</requirement>
    </requirements>
    <command detect_errors="exit_code"><![CDATA[
        mkdir -p input_dir && unzip -q '$input_zip' -d input_dir &&
        enzywizard-integrate
        -i input_dir
        -o ./
        $strict
    ]]></command>
    <inputs>
        <expand macro="zip_input_dir" name="input_zip" label="Input report directory (zip)" help="Zip archive containing EnzyWizard JSON reports to integrate." optional="false"/>
        <expand macro="strict"/>
    </inputs>
    <outputs>
        <expand macro="output_collection" name="output_files" label="${tool.name} outputs"/>
    </outputs>
    <tests>
        <test expect_num_outputs="1">
            <param name="input_zip" value="integrate_input.zip"/>
            <output_collection name="output_files" type="list" min="1"/>
        </test>
    </tests>
    <help><![CDATA[
Integrate multiple EnzyWizard JSON reports into a graph representation. Directory inputs are represented as zip datasets and unpacked explicitly inside this wrapper command in the Galaxy job working directory. Outputs are exposed as discovered dataset collections.
    ]]></help>
    <expand macro="creator"/>
</tool>
