<tool id="utils.descend_classes_and_funcs" name="utils.descend_classes_and_funcs" version="1.3.1+galaxy1">
  <macros>
    <import>macros.xml</import>
  </macros>
  <expand macro="requirements"/>
  <command detect_errors="exit_code"><![CDATA[
        python $script_file
    ]]></command>
  <inputs>
    </inputs>
  <configfiles>
    <configfile name="script_file"><![CDATA[
import scanpy.api as sc



sc.utils.descend_classes_and_funcs()
]]></configfile>
  </configfiles>
  <outputs>
    </outputs>
  <help><![CDATA[
        TODO: Fill in help.
    ]]></help>
  <tests>
    <test/>
  </tests>
  <expand macro="citations"/>
</tool>
