<tool id="trackastra_track" name="Trackastra track" version="@TOOL_VERSION@+galaxy@VERSION_SUFFIX@" profile="@PROFILE@" license="BSD-3-Clause">
    <description>link segmented objects across a microscopy time series</description>
    <macros>
        <import>macros.xml</import>
    </macros>
    <edam_topics>
        <edam_topic>topic_3474</edam_topic>
    </edam_topics>
    <edam_operations>
        <edam_operation>operation_2944</edam_operation>
    </edam_operations>
    <expand macro="requirements"/>
    <version_command>trackastra --help 2&gt;&amp;1 | head -n 1; python -c "import importlib.metadata; print(importlib.metadata.version('trackastra'))"</version_command>
    <command detect_errors="exit_code"><![CDATA[
mkdir -p 'ctc_output' 'home' &&
export HOME="\$PWD/home" &&
export OMP_NUM_THREADS="\${GALAXY_SLOTS:-1}" &&
export MKL_NUM_THREADS="\${GALAXY_SLOTS:-1}" &&
#set $images_path = 'images'
#set $masks_path = 'masks'

#if $inputs.input_format == 'collections':
    mkdir -p 'images' 'masks' &&
    #for $i, $image in enumerate($inputs.images):
        #set $frame = '%04d' % $i
        ln -s '$image' 'images/image_${frame}.tif' &&
    #end for
    #for $i, $mask in enumerate($inputs.masks):
        #set $frame = '%04d' % $i
        ln -s '$mask' 'masks/mask_${frame}.tif' &&
    #end for
    image_count=\$(find 'images' -maxdepth 1 -type l | wc -l) &&
    mask_count=\$(find 'masks' -maxdepth 1 -type l | wc -l) &&
    if [ "\$image_count" -ne "\$mask_count" ]; then
        echo 'The image and mask collections must contain the same number of elements.' >&2;
        exit 1;
    fi &&
#else:
    ln -s '$inputs.images_stack' 'images_stack.tif' &&
    ln -s '$inputs.masks_stack' 'masks_stack.tif' &&
    #set $images_path = 'images_stack.tif'
    #set $masks_path = 'masks_stack.tif'
#end if

#if $model_source.source == 'cached':
    #set $model_path = $model_source.model.fields.path
#else:
    mkdir -p 'custom_model' &&
    ln -s '$model_source.model_weights' 'custom_model/model.pt' &&
    ln -s '$model_source.architecture_config' 'custom_model/config.yaml' &&
    ln -s '$model_source.training_config' 'custom_model/train_config.yaml' &&
    #set $model_path = 'custom_model'
#end if

trackastra track --imgs '$images_path' --masks '$masks_path' --output-ctc 'ctc_output' --output-edge-table 'edge_table.csv' --model-custom '$model_path' --mode '$mode' --max-distance '$max_distance'
    ]]></command>
    <inputs>
        <conditional name="inputs">
            <param name="input_format" type="select" label="Input organization">
                <option value="collections" selected="true">Ordered collections: one TIFF per time point</option>
                <option value="stacks">Two multi-page TIFF time-series datasets</option>
            </param>
            <when value="collections">
                <param name="images" type="data_collection" collection_type="list" format="tiff" label="Microscopy images" help="Ordered list collection containing one image TIFF per time point. List order defines time."/>
                <param name="masks" type="data_collection" collection_type="list" format="tiff" label="Instance-segmentation masks" help="Ordered list collection containing one integer-labelled mask TIFF per time point. The number and order of elements must match the image collection."/>
            </when>
            <when value="stacks">
                <param name="images_stack" type="data" format="tiff" label="Microscopy image time series" help="Multi-page TIFF with shape T,(C),(Z),Y,X."/>
                <param name="masks_stack" type="data" format="tiff" label="Instance-segmentation mask time series" help="Integer-labelled multi-page TIFF with shape T,(Z),Y,X, matching the image time series."/>
            </when>
        </conditional>
        <conditional name="model_source">
            <param name="source" type="select" label="Trackastra model source">
                <option value="cached" selected="true">Model installed on this Galaxy server</option>
                <option value="history">Model components from history</option>
            </param>
            <when value="cached">
                <param name="model" type="select" label="Installed Trackastra model" help="Models are installed by a Galaxy administrator using the Trackastra model data manager.">
                    <options from_data_table="trackastra_models">
                        <validator type="no_options" message="No Trackastra models are installed on this Galaxy server. Ask an administrator to run the Trackastra model data manager, or select model components from history."/>
                    </options>
                </param>
            </when>
            <when value="history">
                <param name="model_weights" type="data" format="data" label="Model weights (model.pt)" help="Trackastra model state dictionary. Use only a model from a trusted source; Trackastra loads it with PyTorch's weights-only mode."/>
                <param name="architecture_config" type="data" format="yaml" label="Model architecture configuration (config.yaml)"/>
                <param name="training_config" type="data" format="yaml" label="Training configuration (train_config.yaml)"/>
            </when>
        </conditional>
        <param argument="--mode" type="select" label="Linking mode">
            <option value="greedy" selected="true">Greedy linking with divisions</option>
            <option value="greedy_nodiv">Greedy linking without divisions</option>
            <option value="ilp">Integer-linear-programming linking</option>
        </param>
        <param argument="--max-distance" type="float" value="128" min="0" label="Maximum linking distance" help="Maximum spatial distance, in pixels or voxels, considered while constructing candidate links."/>
    </inputs>
    <outputs>
        <data name="edge_table" format="csv" from_work_dir="edge_table.csv" label="${tool.name} on ${on_string}: association edge table"/>
        <data name="track_table" format="tabular" from_work_dir="ctc_output/man_track.txt" label="${tool.name} on ${on_string}: CTC track table"/>
        <collection name="tracked_masks" type="list" label="${tool.name} on ${on_string}: tracked masks">
            <discover_datasets pattern="man_track(?P&lt;designation&gt;[0-9]+)\.tif" format="tiff" directory="ctc_output"/>
        </collection>
    </outputs>
    <tests>
        <test expect_num_outputs="3">
            <conditional name="inputs">
                <param name="input_format" value="collections"/>
                <param name="images">
                    <collection type="list">
                        <element name="t0000" ftype="tiff" value="image_0000.tif"/>
                        <element name="t0001" ftype="tiff" value="image_0001.tif"/>
                        <element name="t0002" ftype="tiff" value="image_0002.tif"/>
                    </collection>
                </param>
                <param name="masks">
                    <collection type="list">
                        <element name="t0000" ftype="tiff" value="mask_0000.tif"/>
                        <element name="t0001" ftype="tiff" value="mask_0001.tif"/>
                        <element name="t0002" ftype="tiff" value="mask_0002.tif"/>
                    </collection>
                </param>
            </conditional>
            <conditional name="model_source">
                <param name="source" value="cached"/>
                <param name="model" value="tiny_test"/>
            </conditional>
            <param name="mode" value="greedy_nodiv"/>
            <param name="max_distance" value="32"/>
            <output name="edge_table" ftype="csv">
                <assert_contents>
                    <has_n_lines n="3"/>
                    <has_line line="source_frame,source_label,target_frame,target_label,weight"/>
                    <has_line_matching expression="^0,1,1,1,[0-9.eE+-]+$"/>
                    <has_line_matching expression="^1,1,2,1,[0-9.eE+-]+$"/>
                </assert_contents>
            </output>
            <output name="track_table" file="expected_man_track.txt" ftype="tabular"/>
            <output_collection name="tracked_masks" type="list" count="3">
                <element name="0000" ftype="tiff">
                    <assert_contents>
                        <has_size min="100"/>
                    </assert_contents>
                </element>
                <element name="0001" ftype="tiff">
                    <assert_contents>
                        <has_size min="100"/>
                    </assert_contents>
                </element>
                <element name="0002" ftype="tiff">
                    <assert_contents>
                        <has_size min="100"/>
                    </assert_contents>
                </element>
            </output_collection>
        </test>
        <test expect_num_outputs="3">
            <conditional name="inputs">
                <param name="input_format" value="stacks"/>
                <param name="images_stack" value="images_stack.tif" ftype="tiff"/>
                <param name="masks_stack" value="masks_stack.tif" ftype="tiff"/>
            </conditional>
            <conditional name="model_source">
                <param name="source" value="history"/>
                <param name="model_weights" value="tiny_model/model.pt" ftype="data"/>
                <param name="architecture_config" value="tiny_model/config.yaml" ftype="yaml"/>
                <param name="training_config" value="tiny_model/train_config.yaml" ftype="yaml"/>
            </conditional>
            <param name="mode" value="greedy"/>
            <param name="max_distance" value="32"/>
            <output name="edge_table" ftype="csv">
                <assert_contents>
                    <has_n_lines n="3"/>
                    <has_text text="source_frame,source_label,target_frame,target_label,weight"/>
                </assert_contents>
            </output>
            <output name="track_table" file="expected_man_track.txt" ftype="tabular"/>
            <output_collection name="tracked_masks" type="list" count="3"/>
        </test>
        <test expect_failure="true" expect_exit_code="1">
            <conditional name="inputs">
                <param name="input_format" value="collections"/>
                <param name="images">
                    <collection type="list">
                        <element name="t0000" ftype="tiff" value="image_0000.tif"/>
                        <element name="t0001" ftype="tiff" value="image_0001.tif"/>
                    </collection>
                </param>
                <param name="masks">
                    <collection type="list">
                        <element name="t0000" ftype="tiff" value="mask_0000.tif"/>
                    </collection>
                </param>
            </conditional>
            <conditional name="model_source">
                <param name="source" value="cached"/>
                <param name="model" value="tiny_test"/>
            </conditional>
            <assert_stderr>
                <has_text text="must contain the same number of elements"/>
            </assert_stderr>
        </test>
    </tests>
    <help><![CDATA[
**Trackastra** associates objects that have already been segmented in a microscopy time series. It does not perform segmentation.

Input organization
==================

Use either two ordered Galaxy list collections or two multi-page TIFF datasets. Images and masks must have matching time points and spatial dimensions. Masks must be integer-labelled instance segmentations; background is label 0.

Models
======

For reproducible execution, pretrained models are installed once by a Galaxy administrator with the accompanying Trackastra model data manager. This avoids downloading model files during ordinary analysis jobs. A complete custom model can instead be supplied from history as ``model.pt``, ``config.yaml``, and ``train_config.yaml``.

Trackastra loads ``model.pt`` with PyTorch ``weights_only=True``. Nevertheless, use custom model files only when their origin is trusted.

Linking modes
=============

- **greedy**: fast linking that permits cell divisions.
- **greedy_nodiv**: fast linking without divisions.
- **ilp**: integer-linear-programming linking. This is slower and depends on a solver available in the Trackastra environment.

Resources
=========

The wrapper sets common numerical-library thread limits from the CPU allocation selected by the Galaxy job destination through ``GALAXY_SLOTS``. Trackastra's feature extraction worker count and inference batch size use their upstream defaults. CPU/GPU placement is intentionally not exposed as a user parameter; Trackastra automatically uses CUDA when the administrator routes the job to a compatible GPU destination.

Outputs
=======

- **Association edge table**: CSV containing source/target frame and label identifiers plus association weights.
- **CTC track table**: space-delimited ``track_id start_frame end_frame parent_track_id`` records.
- **Tracked masks**: an ordered collection of relabelled TIFF masks in Cell Tracking Challenge form.
    ]]></help>
    <expand macro="citations"/>
</tool>
