<?xml version="1.0"?>
<tool id="circos_wiggle_to_stacked_histogram" name="Circos: Wiggle to Stacked Histogram" version="@WRAPPER_VERSION@">
    <description>collapses multiple (big)Wig files into a single stacked histogram.</description>
    <macros>
        <import>macros.xml</import>
    </macros>
    <expand macro="requirements">
    </expand>
    <command detect_errors="exit_code"><![CDATA[
python '$__tool_directory__/histogram-from-wiggle.py'
#for file in $inputs:
    '$file'
#end for
 > '$output'
    ]]></command>
    <inputs>
        <param name="input" type="data" format="wig" label="Data files" multiple="true" help="It is imperative that ALL of your wig files use the same step and span, and are of the same type (fixedStep or variableStep)." />
    </inputs>
    <outputs>
        <data name="output" format="tabular" />
    </outputs>
    <tests>
    </tests>
    <help><![CDATA[
Converts standard (big)Wig files into a format appropriate for Circos stacked histogram plot tracks.
    ]]></help>
    <expand macro="citations" />
</tool>
