<?xml version="1.0"?>
<tool_dependency>
    <package name="snippy" version="3.0">
        <install version="1.0">
            <actions_group>
                <actions>
                    <action type="download_by_url" sha256sum="4d9354bd953ee46937870cfd1b7f608e4932b1990b7e73320c888902f7753ff6" >https://github.com/tseemann/snippy/archive/v3.1.tar.gz</action>
                    <action type="move_directory_files">
                        <source_directory>.</source_directory>
                        <destination_directory>$INSTALL_DIR</destination_directory>
                      </action>
                      <action type="shell_command">chmod ugo+x $INSTALL_DIR/bin/snippy</action>
                </actions>
                <actions architecture="x86_64" os="linux">
                    <action type="set_environment">
                        <environment_variable name="PATH" action="prepend_to">$INSTALL_DIR/bin:$INSTALL_DIR/binaries/noarch:$INSTALL_DIR/binaries/linux</environment_variable>
                    </action>
                </actions>
                <actions architecture="x86_64" os="darwin">
                    <action type="set_environment">
                        <environment_variable name="PATH" action="prepend_to">$INSTALL_DIR/bin:$INSTALL_DIR/binaries/noarch:$INSTALL_DIR/binaries/linux</environment_variable>
                    </action>
                </actions>                  
            </actions_group>
        </install>
    </package>
</tool_dependency>
