<?xml version="1.0"?>
<tool_dependency>
    <package name="perl" version="5.18.1">
        <repository name="package_perl_5_18" owner="iuc" prior_installation_required="True" />
    </package>
    <package name="bioperl" version="1.6.922">
        <install version="1.0">
            <actions>
                <action type="setup_perl_environment">
                    <repository name="package_perl_5_18" owner="iuc">
                        <package name="perl" version="5.18.1" />
                    </repository>
                   <package sha256sum="da8a88112bff0224bd17b74eb28f605f96db6481ed5c8c00ca7e851522deee2b">
                       https://depot.galaxyproject.org/software/BioPerl/BioPerl_1.6.922_src_all.tar.gz
                   </package>
                </action>
            </actions>
        </install>
        <readme>
            Bundle::BioPerl
        </readme>
    </package>
</tool_dependency>
