<macros>
    <token name="@TOOL_VERSION@">1.14.0</token>
    <token name="@SUFFIX_VERSION@">0</token>
    <xml name="edam_ontology">
        <edam_topics>                                                                                  
            <edam_topic>topic_0080</edam_topic>
        </edam_topics>
        <edam_operations>
            <edam_operation>operation_2403</edam_operation>
        </edam_operations>
    </xml>
    <xml name="requirements">
        <requirements>
            <requirement type="package" version="@TOOL_VERSION@">bioconductor-amplican</requirement>
            <requirement type="package" version="1.20.3">r-getopt</requirement>
        </requirements>
    </xml>
    <xml name="citations">
        <citations>
            <citation type="doi">10.1101/gr.244293.118</citation>
        </citations>
    </xml>
</macros>
