<macros>
    <token name="@TOOL_VERSION@">1.1.9</token>
    <token name="@PROFILE@">23.1</token>
    <xml name="bio_tools">
        <xrefs>
            <xref type="bio.tools">hamronization</xref>
        </xrefs>
    </xml>
    <xml name="requirements">
        <requirements>
            <requirement type="package" version="@TOOL_VERSION@">hamronization</requirement>
        </requirements>
    </xml>
    <xml name="version_command">
        <version_command>hamronize --version</version_command>
    </xml>
    <xml name="report" token_format="tabular" token_label="Report" >
        <param argument="report" type="data" format="@FORMAT@" label="@LABEL@"/>
    </xml>
    <xml name="input_file_name">
        <param argument="--input_file_name" type="text" label="Sample name" help="If not provided, the input dataset will be taken"/>
    </xml>
    <xml name="analysis_software_version" token_software="">
        <param argument="--analysis_software_version" type="text" label="@SOFTWARE@ version"/>
    </xml>
    <xml name="reference_database_version">
        <param name="reference_database_version" type="text" label="Reference database version"/>
    </xml>
    <xml name="origin" token_software="">
        <conditional name="origin">
            <param name="origin" type="select" label="Input generated within Galaxy on this server without leaving it?">
                <option value="true" selected="true">Yes</option>
                <option value="false">No</option>
            </param>
            <when value="true"/>
            <when value="false">
                <expand macro="analysis_software_version" software="@SOFTWARE@" />
            </when>
        </conditional>
        <expand macro="reference_database_version"/>   
    </xml>
    <xml name="reference_database_name" token_software="">
        <param name="reference_database_name" type="text" label="Reference database name for @SOFTWARE@"/>
    </xml>
    <xml name="citations">
        <citations>
            <citation type="doi">10.5281/zenodo.10015946</citation>
        </citations>
    </xml>
</macros>
